python_antenna_pattern/__init__.py
python_antenna_pattern/cli.py
python_antenna_pattern/cli_back.py
python_antenna_pattern/config.py
python_antenna_pattern/core.py
python_antenna_pattern/parser.py
python_antenna_pattern/python_antenna_pattern.py
python_antenna_pattern/tests.py
python_antenna_pattern-0.0.1.dist-info/AUTHORS.rst
python_antenna_pattern-0.0.1.dist-info/LICENSE
python_antenna_pattern-0.0.1.dist-info/METADATA
python_antenna_pattern-0.0.1.dist-info/WHEEL
python_antenna_pattern-0.0.1.dist-info/entry_points.txt
python_antenna_pattern-0.0.1.dist-info/top_level.txt
python_antenna_pattern-0.0.1.dist-info/RECORD
