Metadata-Version: 2.1
Name: python-antenna-pattern
Version: 0.0.1
Summary: Generate antenna radiation pattern in polar format using python
Home-page: https://github.com/tyc85/python_antenna_pattern
Author: Tsung-Yi Chen
Author-email: steven.tychen@gmail.com
License: Apache Software License 2.0
Keywords: python_antenna_pattern
Platform: UNKNOWN
Classifier: Development Status :: 2 - Pre-Alpha
Classifier: Intended Audience :: Developers
Classifier: License :: OSI Approved :: Apache Software License
Classifier: Natural Language :: English
Classifier: Programming Language :: Python :: 3
Classifier: Programming Language :: Python :: 3.5
Classifier: Programming Language :: Python :: 3.6
Classifier: Programming Language :: Python :: 3.7
Classifier: Programming Language :: Python :: 3.8
Requires-Python: >=3.6
Requires-Dist: numpy
Requires-Dist: matplotlib
